{
  "1240760": {
    "name": "The Adventures of Ten and Till Soundtrack",
    "steam_appid": 1240760,
    "required_age": 0,
    "is_free": false,
    "description": "The original soundtrack of the bullet hell shoot 'em up The Adventures of Ten and Till. This OST was composed by the game's designer Toro Nishino.",
    "supported_languages": "",
    "header_image": "https://shared.akamai.steamstatic.com/store_item_assets/steam/apps/1240760/header.jpg?t=1589207840",
    "developers": [
      "Toro Nishino"
    ],
    "publishers": [
      "LionWing Publishing"
    ],
    "price_overview": {
      "currency": "CNY",
      "initial": 2200,
      "final": 2200,
      "discount_percent": 0,
      "initial_formatted": "",
      "final_formatted": "¥ 22.00"
    },
    "release_date": {
      "coming_soon": false,
      "date": "2020 年 5 月 11 日"
    },
    "categories": [],
    "genres": [],
    "achievements": "none",
    "has_chinese": "false",
    "app_reviews": {
      "review_score_desc": "No user reviews",
      "total_positive": 0,
      "total_negative": 0,
      "total_reviews": 0
    }
  }
}