{
  "1399310": {
    "name": "Blades of Worlds Demo",
    "steam_appid": 1399310,
    "required_age": 0,
    "is_free": true,
    "description": "<strong>Currently the demo is a short demonstration of how the game's tutorial began. It is outdated now. It will be updated in May 2022. (Also the pictures and videos will be updated. Currently they are outdated heavily). </strong><br><br><strong>The game</strong><br><br><strong>In short, the game is:</strong><br><br><ul class=\"bb_ul\"><li>A magical cold nature themed fantasy where you gather viewers like a real life streamer in order to save them from a bad influence<br></li><li>What if live streaming was the way of life, a natural thing. You use water powers as a streamer to move around fast around the world.</li></ul><h2 class=\"bb_tag\" >Streamer is a fantasy, action role-playing game with real life live-streaming influences. </h2><br><strong></strong><br><ul class=\"bb_ul\"><li></li></ul>",
    "supported_languages": "英语",
    "header_image": "https://shared.akamai.steamstatic.com/store_item_assets/steam/apps/1399310/header.jpg?t=1651317807",
    "developers": [
      "Tatu Rikala"
    ],
    "publishers": [
      "Tatu Rikala"
    ],
    "price_overview": {},
    "release_date": {
      "coming_soon": false,
      "date": "2020 年 8 月 25 日"
    },
    "categories": [
      {
        "id": 2,
        "description": "单人"
      },
      {
        "id": 10,
        "description": "游戏试用版"
      },
      {
        "id": 28,
        "description": "完全支持控制器"
      }
    ],
    "genres": [],
    "achievements": "none",
    "has_chinese": "false",
    "app_reviews": {
      "review_score_desc": "No user reviews",
      "total_positive": 0,
      "total_negative": 0,
      "total_reviews": 0
    }
  }
}