{
  "1412000": {
    "name": "Agoraphobia",
    "steam_appid": 1412000,
    "required_age": 0,
    "is_free": false,
    "description": "You awake, You expect your family to greet you, but the house is empty. Something's wrong. Where is everyone? And what's happened to them? Unravel the mystery for yourself in Agoraphobia, a exploration game. Interrogate every detail of a seemingly normal house to discover the story of the people who lived there.<br />\r\n<br />\r\nThe game Agoraphobia is a psychological Horror in the first person.  <br />\r\n<br />\r\nIMPORTANT NOTE. The game was created by one person and Ue4 free and paid content where used to create this game.",
    "supported_languages": "英语<strong>*</strong><br><strong>*</strong>具有完全音频支持的语言",
    "header_image": "https://shared.akamai.steamstatic.com/store_item_assets/steam/apps/1412000/header.jpg?t=1602438088",
    "developers": [
      "Tainted Games"
    ],
    "publishers": [
      "Tainted Games"
    ],
    "price_overview": {
      "currency": "CNY",
      "initial": 600,
      "final": 600,
      "discount_percent": 0,
      "initial_formatted": "",
      "final_formatted": "¥ 6.00"
    },
    "release_date": {
      "coming_soon": false,
      "date": "2020 年 9 月 30 日"
    },
    "categories": [
      {
        "id": 2,
        "description": "单人"
      },
      {
        "id": 22,
        "description": "Steam 成就"
      },
      {
        "id": 62,
        "description": "家庭共享"
      }
    ],
    "genres": [
      {
        "id": "25",
        "description": "冒险"
      },
      {
        "id": "23",
        "description": "独立"
      }
    ],
    "achievements": {
      "total": 17,
      "highlighted": [
        {
          "name": "You Win",
          "path": "https://cdn.akamai.steamstatic.com/steamcommunity/public/images/apps/1412000/7451669044cfb6bc68a148b7856d01c44501c499.jpg"
        },
        {
          "name": "Stay Awhile ",
          "path": "https://cdn.akamai.steamstatic.com/steamcommunity/public/images/apps/1412000/f36e6331e8ec4b07c1f5fbeea2f4e88f2ee81658.jpg"
        },
        {
          "name": "Unlocked",
          "path": "https://cdn.akamai.steamstatic.com/steamcommunity/public/images/apps/1412000/a17966553f696cf4e779ce8b62da10177c1aa4ac.jpg"
        },
        {
          "name": "Ghosts Are Bad",
          "path": "https://cdn.akamai.steamstatic.com/steamcommunity/public/images/apps/1412000/0c17b316416fb28f4ebe770dada77f12dd94419c.jpg"
        },
        {
          "name": "Darkness",
          "path": "https://cdn.akamai.steamstatic.com/steamcommunity/public/images/apps/1412000/86a3d835369bc90c892a877ed7e4f0c513cb0dff.jpg"
        },
        {
          "name": "Bones",
          "path": "https://cdn.akamai.steamstatic.com/steamcommunity/public/images/apps/1412000/f36419610b66d5b1043cebb0c2bc248baa190d52.jpg"
        },
        {
          "name": "Booked",
          "path": "https://cdn.akamai.steamstatic.com/steamcommunity/public/images/apps/1412000/5fb115c215d720f821c2ac1fb65e979bd91dedd2.jpg"
        },
        {
          "name": "Notes Are Rare",
          "path": "https://cdn.akamai.steamstatic.com/steamcommunity/public/images/apps/1412000/bac619dbd66eb57fe4b8f3e93e88324d6cedf518.jpg"
        },
        {
          "name": "You Quitter ",
          "path": "https://cdn.akamai.steamstatic.com/steamcommunity/public/images/apps/1412000/3ff6a6ac32bc123f33049f1ad25340bf821b97b3.jpg"
        },
        {
          "name": "Puzzled",
          "path": "https://cdn.akamai.steamstatic.com/steamcommunity/public/images/apps/1412000/0aba3affd1e0f8912b66f0884af5d5cb23630f98.jpg"
        }
      ]
    },
    "has_chinese": "false",
    "app_reviews": {
      "review_score_desc": "4 user reviews",
      "total_positive": 0,
      "total_negative": 4,
      "total_reviews": 4
    }
  }
}