{
  "1506980": {
    "name": "葬花·暗黑桃花源",
    "steam_appid": 1506980,
    "required_age": 0,
    "is_free": false,
    "description": "<strong>“南阳刘子骥，高尚士也，闻之，欣然规往。”</strong><br><br>葬花交流群【昼】（已满）：1065118919  <br>葬花交流群【夜】（已满）：779247604  <br>葬花交流群【夕】（新群）：915072723 欢迎加入！<br><br><span class=\"bb_img_ctn\"><img class=\"bb_img\" src=\"https://shared.akamai.steamstatic.com/store_item_assets/steam/apps/1506980/extras/418ad48a9c573be530a2f7a6f882c154.avif?t=1757041321\" width=471 height=94 /></span><br><br>“晋太元中，武陵人捕鱼为业。缘溪行，忘路之远近。忽逢桃花林......”<br>千年来，无数旅人迷途山中，想找寻那传说中的世外桃源。<br>他们或流连忘返，或辞去后不复得路，或寻病而终。<br>在他们传颂于世的描述中：这里似乎是一个至臻至美的乌托邦。<br>可若是这乌托邦永恒不变，又何尝不是另一种形态的地狱？<br>埋葬于历史尘埃中的呼钺国，掌握着千古一帝求之不得的长生不老秘术——代价又是什么？<br>桃花落尽枯骨香，彼岸花开越千年。<br>留守其中的九百魂灵，渴望着“葬花之人”的到来。<br>白昼的她，想和你去看外面的世界，看那阔别千年的车水马龙。<br>夜晚的她，期许你将这一切彻底地埋葬.....<br><br><span class=\"bb_img_ctn\"><img class=\"bb_img\" src=\"https://shared.akamai.steamstatic.com/store_item_assets/steam/apps/1506980/extras/db7c5cd0780a75d3227f452d26c41995.avif?t=1757041321\" width=471 height=94 /></span><br><br><span class=\"bb_img_ctn\"><img class=\"bb_img\" src=\"https://shared.akamai.steamstatic.com/store_item_assets/steam/apps/1506980/extras/e4755f989e1321672c85a81cd011aabd.avif?t=1757041321\" width=473 height=238 /></span><br><br><i>“能带我看看吗？外面的世界。”<br>司掌祭祀的神女，据说是指引大家来桃花源避难的山神的后代。<br>温柔善良，对外面的世界充满好奇。<br><br><span class=\"bb_img_ctn\"><img class=\"bb_img\" src=\"https://shared.akamai.steamstatic.com/store_item_assets/steam/apps/1506980/extras/db84f06db3ec7abfa78894baa95f9b94.avif?t=1757041321\" width=473 height=238 /></span><br><i>“白天定的规矩，在晚上并不适用。”</i><br>夜晚出现的神秘少女，和白天的双花长相一样，性格却截然不同。<br>时而清冷高贵，时而妩媚风情。<br>在桃花源内，她拥有掌控万物的神力。<br><br><span class=\"bb_img_ctn\"><img class=\"bb_img\" src=\"https://shared.akamai.steamstatic.com/store_item_assets/steam/apps/1506980/extras/6795ffd92c39e067f0386d3cf90937c1.avif?t=1757041321\" width=472 height=238 /></span><br>村中失忆的少女，似乎和解开谜团有关。<br><br><span class=\"bb_img_ctn\"><img class=\"bb_img\" src=\"https://shared.akamai.steamstatic.com/store_item_assets/steam/apps/1506980/extras/c5e75a646157f07e4766c32c47c832ec.avif?t=1757041321\" width=473 height=238 /></span><br>白天是织布的寡妇，晚上是砍人的剑圣。<br><br><span class=\"bb_img_ctn\"><img class=\"bb_img\" src=\"https://shared.akamai.steamstatic.com/store_item_assets/steam/apps/1506980/extras/96a7cf656d2f979facbce58890cea67e.avif?t=1757041321\" width=473 height=238 /></span><br>白天是和蔼的老村长，晚上一直很饥饿。<br><br><span class=\"bb_img_ctn\"><img class=\"bb_img\" src=\"https://shared.akamai.steamstatic.com/store_item_assets/steam/apps/1506980/extras/6c1088f81f2a3eb26bde1339a4596bae.avif?t=1757041321\" width=473 height=238 /></span><br>村里的猎人兼屠户，由他来送村里的牲畜上路。<br><br><span class=\"bb_img_ctn\"><img class=\"bb_img\" src=\"https://shared.akamai.steamstatic.com/store_item_assets/steam/apps/1506980/extras/47f4ebe8fe2adca64939eef6eb6f30dc.avif?t=1757041321\" width=472 height=238 /></span><br>村里的熊孩子，喜欢斗蟋蟀。<br><br><span class=\"bb_img_ctn\"><img class=\"bb_img\" src=\"https://shared.akamai.steamstatic.com/store_item_assets/steam/apps/1506980/extras/b157223b8b359d9b6c2696540c87c845.avif?t=1757041321\" width=471 height=94 /></span><br>超高自由度，20万字不重复文本，20个不同的结局。<br>尽情选择体验喜欢的剧情，从不同的角度去体验探索桃花源。<br>村中神女、失忆妹妹、貌美寡妇、年老村长、猛男猎人都是可攻略角色，有人物专属的恋爱（或友情）结局。<br>一周目锁定部分选项，多周目重玩会开启隐藏选项。<br><br><span class=\"bb_img_ctn\"><img class=\"bb_img\" src=\"https://shared.akamai.steamstatic.com/store_item_assets/steam/apps/1506980/extras/ca45a981cc1e2aedb32460931774c7c2.avif?t=1757041321\" width=471 height=94 /></span><br>日式厚涂画风，国风元素，追求精细度的极致。<br>严谨考究秦汉服装的特点设计服装和村庄环境。<br>美术将围绕“昼与夜”、“桃花与彼岸“，”生与死“等多个对立主题创作。<br><br><span class=\"bb_img_ctn\"><img class=\"bb_img\" src=\"https://shared.akamai.steamstatic.com/store_item_assets/steam/apps/1506980/extras/92c1ffc3b57ba5227fcac9d6878df49b.avif?t=1757041321\" width=471 height=94 /></span><br>全语音配音<br>知名UP主、配音演员、唱见“Hanser”负责女主角配音，献声600句以上。<br>森中人担任配音导演的工作，可保证带来专业优秀的AVG配音。<br><br><span class=\"bb_img_ctn\"><img class=\"bb_img\" src=\"https://shared.akamai.steamstatic.com/store_item_assets/steam/apps/1506980/extras/8906829115f6991c3e36e0b3fca06042.avif?t=1757041321\" width=471 height=94 /></span><br>制作国产AVG口碑佳作《泡沫冬景》的Nekoday工作室协助研发。<br>Nekoday工作室负责UI设计、PV设计、美宣设计、音效设计、配乐设计的工作。<br><br><span class=\"bb_img_ctn\"><img class=\"bb_img\" src=\"https://shared.akamai.steamstatic.com/store_item_assets/steam/apps/1506980/extras/97431ca9aedf28e7c571e54b64cdbb25.avif?t=1757041321\" width=471 height=94 /></span><br>【Staff】<br>制作组：零创游戏·《葬花》制作组<br>制作人/剧本/演出：嵇零<br>场景原画：fronzenX<br>角色原画：慢慢<br>CG: 慢慢、叉子、fronzenX<br>程序：薪魂、雨夜、三金<br>监制：凶真<br>美术协助：小骨头<br>配乐：Candy_wind<br>配音导演：森中人<br>配音演员：Hanser、朱婧、巫蛊悠悠、魏一凡、蔡书瑾、花玲、柳知萧、森中人、音匣老鬼、kinsen、李沁纹、Mic、芥末、唐睿、默伶、貔貅肛、伊泽小K<br>外包对接：古落（Nekoday)<br>UI设计/PV设计/美宣设计：匣中猫（Nekoday)<br>部分音效/配乐：卡特团长（Nekoday)<br>外包项目管理：拾肆（Nekoday)<br>产品顾问：HD（龍之咲）<br>测试：Ice_935，九月，Rachelle<br><br>零创游戏制作组在小黑盒有开通官方账号，定期分享制作杂谈等相关内容，直接搜索@零创游戏 即可关注。欢迎加入小黑盒社区！</i>",
    "supported_languages": "简体中文<strong>*</strong>, 繁体中文<strong>*</strong>, 英语<br><strong>*</strong>具有完全音频支持的语言",
    "header_image": "https://shared.akamai.steamstatic.com/store_item_assets/steam/apps/1506980/header_schinese.jpg?t=1757041321",
    "developers": [
      "零创游戏(ZerocreationGame)"
    ],
    "publishers": [
      "零创游戏(ZerocreationGame)"
    ],
    "price_overview": {
      "currency": "CNY",
      "initial": 4500,
      "final": 4500,
      "discount_percent": 0,
      "initial_formatted": "",
      "final_formatted": "¥ 45.00"
    },
    "release_date": {
      "coming_soon": false,
      "date": "2021 年 10 月 21 日"
    },
    "categories": [
      {
        "id": 2,
        "description": "单人"
      },
      {
        "id": 22,
        "description": "Steam 成就"
      },
      {
        "id": 23,
        "description": "Steam 云"
      },
      {
        "id": 62,
        "description": "家庭共享"
      }
    ],
    "genres": [
      {
        "id": "25",
        "description": "冒险"
      },
      {
        "id": "4",
        "description": "休闲"
      },
      {
        "id": "23",
        "description": "独立"
      },
      {
        "id": "3",
        "description": "角色扮演"
      }
    ],
    "achievements": {
      "total": 34,
      "highlighted": [
        {
          "name": "世外桃源",
          "path": "https://cdn.akamai.steamstatic.com/steamcommunity/public/images/apps/1506980/0b4465de7254a0ec3ddf34530acbe1b325d3f389.jpg"
        },
        {
          "name": "宇〇波后裔",
          "path": "https://cdn.akamai.steamstatic.com/steamcommunity/public/images/apps/1506980/b73a6c9485b22fcdf3b2f5186733900c0a664084.jpg"
        },
        {
          "name": "为时尚早",
          "path": "https://cdn.akamai.steamstatic.com/steamcommunity/public/images/apps/1506980/b841d8eb57c8f0f0368616159a141d9c6b5cb52d.jpg"
        },
        {
          "name": "社会险恶",
          "path": "https://cdn.akamai.steamstatic.com/steamcommunity/public/images/apps/1506980/7d4420d292fecfb4e807fbf0a36230566bcc25a4.jpg"
        },
        {
          "name": "机智如我",
          "path": "https://cdn.akamai.steamstatic.com/steamcommunity/public/images/apps/1506980/546c348789dd9e04be3358ba2165f3b75003e68c.jpg"
        },
        {
          "name": "你为什么只是看着啊！",
          "path": "https://cdn.akamai.steamstatic.com/steamcommunity/public/images/apps/1506980/6665730473b0a1cb29dab41af70316eede330697.jpg"
        },
        {
          "name": "我全都想起来了！",
          "path": "https://cdn.akamai.steamstatic.com/steamcommunity/public/images/apps/1506980/2ef24ca0dc35a5e5ce7a3a373ff03ffc2f5cc8ea.jpg"
        },
        {
          "name": "直觉大师",
          "path": "https://cdn.akamai.steamstatic.com/steamcommunity/public/images/apps/1506980/010956b65d1ff76e47b1ba31c6f65b71e9b16453.jpg"
        },
        {
          "name": "神像的奇妙用途",
          "path": "https://cdn.akamai.steamstatic.com/steamcommunity/public/images/apps/1506980/80c766979703b59e1982c547adadb7ae0d8b9e04.jpg"
        },
        {
          "name": "独行侠",
          "path": "https://cdn.akamai.steamstatic.com/steamcommunity/public/images/apps/1506980/f4736da7e0eb1264234fa5692601f5d7fb7b5be8.jpg"
        }
      ]
    },
    "has_chinese": "true",
    "app_reviews": {
      "review_score_desc": "Overwhelmingly Positive",
      "total_positive": 5500,
      "total_negative": 257,
      "total_reviews": 5757
    }
  }
}