{
  "1511190": {
    "name": "Super Toy Cars Offroad",
    "steam_appid": 1511190,
    "required_age": 0,
    "is_free": false,
    "description": "<span class=\"bb_img_ctn\"><img class=\"bb_img\" src=\"https://shared.akamai.steamstatic.com/store_item_assets/steam/apps/1511190/extras/ce3140b1ba8ffa8a57c2f950857d87a8.avif?t=1645201440\" width=616 height=216 /></span><br><span class=\"bb_img_ctn\"><video class=\"bb_img\" autoplay muted loop playsinline poster=\"https://shared.akamai.steamstatic.com/store_item_assets/steam/apps/1511190/extras/e29ad491bf400d8f08966f68f45d15c6.poster.avif?t=1645201440\" width=616 height=274 ><source src=\"https://shared.akamai.steamstatic.com/store_item_assets/steam/apps/1511190/extras/e29ad491bf400d8f08966f68f45d15c6.webm?t=1645201440\" type=\"video/webm; codecs=vp9\"><source src=\"https://shared.akamai.steamstatic.com/store_item_assets/steam/apps/1511190/extras/e29ad491bf400d8f08966f68f45d15c6.mp4?t=1645201440\" type=\"video/mp4\"></video></span><br>《Super Toy Cars 越野版》让该系列游戏离开赛道，深入体验泥浆、黄沙、冰雪以及更多精彩刺激的环境！在这款快节奏的街机风格竞速游戏中找到适合自己的方式，你可以控制迷你越野车辆，飞速穿越堆满了超大号日用物品的精彩赛道。<br><br>驱使你的越野车辆，深入其他玩具从未涉足的地方！在防晒霜和沙堡之间滚烫的海边细沙上留下你自己的车辙印，或者深入巨大的滑雪板和滑雪眼镜围成的神秘雪域，或者选择游戏中提供的 15 款细节分明的赛道尽情驰骋。<br><br><span class=\"bb_img_ctn\"><video class=\"bb_img\" autoplay muted loop playsinline poster=\"https://shared.akamai.steamstatic.com/store_item_assets/steam/apps/1511190/extras/b3fb69d6f72bdcf4064c94ce29b778f7.poster.avif?t=1645201440\" width=616 height=274 ><source src=\"https://shared.akamai.steamstatic.com/store_item_assets/steam/apps/1511190/extras/b3fb69d6f72bdcf4064c94ce29b778f7.webm?t=1645201440\" type=\"video/webm; codecs=vp9\"><source src=\"https://shared.akamai.steamstatic.com/store_item_assets/steam/apps/1511190/extras/b3fb69d6f72bdcf4064c94ce29b778f7.mp4?t=1645201440\" type=\"video/mp4\"></video></span><br><br>在《Super Toy Cars 越野版》，你可以选择 20 种截然不同的车辆，包括 ATV、儿童车、小汽车和个头硕大的卡车。挑选一辆速度快的车辆固然重要，但同样要结实耐用！对手绝不会对你手软，最重要的是个头，所以在选择时要深思熟虑，用你的车轮碾压对手，或者让他们望尘莫及！<br><br><span class=\"bb_img_ctn\"><video class=\"bb_img\" autoplay muted loop playsinline poster=\"https://shared.akamai.steamstatic.com/store_item_assets/steam/apps/1511190/extras/e17a5e493bb162b45014f4a9596726a1.poster.avif?t=1645201440\" width=616 height=274 ><source src=\"https://shared.akamai.steamstatic.com/store_item_assets/steam/apps/1511190/extras/e17a5e493bb162b45014f4a9596726a1.webm?t=1645201440\" type=\"video/webm; codecs=vp9\"><source src=\"https://shared.akamai.steamstatic.com/store_item_assets/steam/apps/1511190/extras/e17a5e493bb162b45014f4a9596726a1.mp4?t=1645201440\" type=\"video/mp4\"></video></span><br><br>在其他任何游戏中，你都不会更好地体验到小时候度假或去游乐场时用玩具车玩耍的感觉。扣紧安全带，感受《Super Toy Cars》新推出的越野冒险之旅吧！<br><br><span class=\"bb_img_ctn\"><video class=\"bb_img\" autoplay muted loop playsinline poster=\"https://shared.akamai.steamstatic.com/store_item_assets/steam/apps/1511190/extras/aaa825b982e703a01d8ad83bc1658b12.poster.avif?t=1645201440\" width=600 height=338 ><source src=\"https://shared.akamai.steamstatic.com/store_item_assets/steam/apps/1511190/extras/aaa825b982e703a01d8ad83bc1658b12.webm?t=1645201440\" type=\"video/webm; codecs=vp9\"><source src=\"https://shared.akamai.steamstatic.com/store_item_assets/steam/apps/1511190/extras/aaa825b982e703a01d8ad83bc1658b12.mp4?t=1645201440\" type=\"video/mp4\"></video></span>",
    "supported_languages": "英语, 法语, 意大利语, 德语, 西班牙语 - 西班牙, 葡萄牙语 - 巴西",
    "header_image": "https://shared.akamai.steamstatic.com/store_item_assets/steam/apps/1511190/header.jpg?t=1645201440",
    "developers": [
      "Eclipse Games"
    ],
    "publishers": [
      "Eclipse Games"
    ],
    "price_overview": {
      "currency": "CNY",
      "initial": 7000,
      "final": 7000,
      "discount_percent": 0,
      "initial_formatted": "",
      "final_formatted": "¥ 70.00"
    },
    "release_date": {
      "coming_soon": false,
      "date": "2022 年 2 月 18 日"
    },
    "categories": [
      {
        "id": 2,
        "description": "单人"
      },
      {
        "id": 1,
        "description": "多人"
      },
      {
        "id": 49,
        "description": "玩家对战"
      },
      {
        "id": 37,
        "description": "同屏/分屏玩家对战"
      },
      {
        "id": 24,
        "description": "同屏/分屏"
      },
      {
        "id": 22,
        "description": "Steam 成就"
      },
      {
        "id": 23,
        "description": "Steam 云"
      },
      {
        "id": 44,
        "description": "远程同乐"
      },
      {
        "id": 62,
        "description": "家庭共享"
      }
    ],
    "genres": [
      {
        "id": "23",
        "description": "独立"
      },
      {
        "id": "9",
        "description": "竞速"
      },
      {
        "id": "18",
        "description": "体育"
      }
    ],
    "achievements": {
      "total": 17,
      "highlighted": [
        {
          "name": "First Victory",
          "path": "https://cdn.akamai.steamstatic.com/steamcommunity/public/images/apps/1511190/ef2f2130fe5d3d0cf6a9d33094ce14eab58274d4.jpg"
        },
        {
          "name": "Better with a Friend",
          "path": "https://cdn.akamai.steamstatic.com/steamcommunity/public/images/apps/1511190/96347015bfca7147c1614341ad23395cea1f4620.jpg"
        },
        {
          "name": "Winner",
          "path": "https://cdn.akamai.steamstatic.com/steamcommunity/public/images/apps/1511190/76900a5b9a0521ea0bace1cb0b798b8612538192.jpg"
        },
        {
          "name": "Long Trip",
          "path": "https://cdn.akamai.steamstatic.com/steamcommunity/public/images/apps/1511190/2479e46f1b4b1d04d13920244882bd2f4fe00740.jpg"
        },
        {
          "name": "First Cup Finished",
          "path": "https://cdn.akamai.steamstatic.com/steamcommunity/public/images/apps/1511190/20284f351cf290ce1876c5cec80ac724ea83e512.jpg"
        },
        {
          "name": "Half-Way Through",
          "path": "https://cdn.akamai.steamstatic.com/steamcommunity/public/images/apps/1511190/798f8b62b6b24e3f64e8b41ef60e7b223227b9ad.jpg"
        },
        {
          "name": "All the Way Through",
          "path": "https://cdn.akamai.steamstatic.com/steamcommunity/public/images/apps/1511190/17cf50e523a81113c9ab6e13685f699dcaee6655.jpg"
        },
        {
          "name": "Vehicle Collector",
          "path": "https://cdn.akamai.steamstatic.com/steamcommunity/public/images/apps/1511190/6f0fd61b2640b9cd46b09f13824c0d6ed2747f3c.jpg"
        },
        {
          "name": "Paintjob Collector",
          "path": "https://cdn.akamai.steamstatic.com/steamcommunity/public/images/apps/1511190/ab43df04b5783a451c355a3ce2cea0bdbe993a06.jpg"
        },
        {
          "name": "Fully Upgraded",
          "path": "https://cdn.akamai.steamstatic.com/steamcommunity/public/images/apps/1511190/c9f9b996699f7124425211c4da7a723ec2160b02.jpg"
        }
      ]
    },
    "has_chinese": "false",
    "app_reviews": {
      "review_score_desc": "1 user reviews",
      "total_positive": 1,
      "total_negative": 0,
      "total_reviews": 1
    }
  }
}