{
  "1544720": {
    "name": "4th & Inches",
    "steam_appid": 1544720,
    "required_age": 0,
    "is_free": false,
    "description": "<strong>The original megahit from Accolade™. <i>Team Construction Disk</i> add-on is included for full team customization options!</strong><br><br>4th &amp; Inches paved the way for modern football games with robust play-calling and team management options, plus satisfying action that puts the player at the center of the on-field play on offense and defense. This classic remains a blast in games against the CPU or with a friend in local multiplayer.<br><br><strong>Welcome to the pros, rookie.</strong><br><br>So you were an All-American? Big deal! This is pro football, baby. It's time to put down your press clippings and start buttin' heads with the big boys.<br><br>4th &amp; Inches gives you all of the hard-hitting action of real football: the bombs, the blitzing, the goal line stands. You'll experience graphics and animation that are as powerful as a blindside hit.<br><br>As the key player on defense, you've got to have speed, stamina and smarts. As the quarterback, you've got to read an unforgiving defense that takes no prisoners. Winning at 4th &amp; Inches will take all the moves of a #1 draft choice plus the tactical genius of a veteran head coach.<br><br>Remember, this is the big time, hotshot. This is real football. This is 4th &amp; Inches.",
    "supported_languages": "英语",
    "header_image": "https://shared.akamai.steamstatic.com/store_item_assets/steam/apps/1544720/header.jpg?t=1614953130",
    "developers": [
      "Accolade"
    ],
    "publishers": [
      "Ziggurat"
    ],
    "price_overview": {
      "currency": "CNY",
      "initial": 2800,
      "final": 2800,
      "discount_percent": 0,
      "initial_formatted": "",
      "final_formatted": "¥ 28.00"
    },
    "release_date": {
      "coming_soon": false,
      "date": "2021 年 3 月 5 日"
    },
    "categories": [
      {
        "id": 2,
        "description": "单人"
      },
      {
        "id": 1,
        "description": "多人"
      },
      {
        "id": 62,
        "description": "家庭共享"
      }
    ],
    "genres": [
      {
        "id": "1",
        "description": "动作"
      },
      {
        "id": "28",
        "description": "模拟"
      },
      {
        "id": "18",
        "description": "体育"
      }
    ],
    "achievements": "none",
    "has_chinese": "false",
    "app_reviews": {
      "review_score_desc": "No user reviews",
      "total_positive": 0,
      "total_negative": 0,
      "total_reviews": 0
    }
  }
}