{
  "1569720": {
    "name": "Attack Of UNDO Zai",
    "steam_appid": 1569720,
    "required_age": 0,
    "is_free": true,
    "description": "Human beings have uncontrolled destruction of the earth' resources, Aliens had sent Angle - Undo Zai to implement the fifth extinction of the earth. This is the final test for humanity.<br><br><strong>Defend Our World</strong><br>4 player need to work together to protect our world from invasion of UNDO Zai. With 4 different ability characters and skills, player can play as a team to help each other challenge the game.<h2 class=\"bb_tag\" >Small Indie Game </h2> <ul class=\"bb_ul\"><li>Single player shooting and challenge the normal or survival game mode. <br></li><li>Multiplayer - 2 to 4 Player team PC shooting game, high definition furry anime characters in a non-stop action shooter.</li></ul><br><span class=\"bb_img_ctn\"><video class=\"bb_img\" autoplay muted loop playsinline poster=\"https://shared.akamai.steamstatic.com/store_item_assets/steam/apps/1569720/extras/094890a683a8b7ce3970311df2ed80db.poster.avif?t=1638279076\" width=640 height=360 ><source src=\"https://shared.akamai.steamstatic.com/store_item_assets/steam/apps/1569720/extras/094890a683a8b7ce3970311df2ed80db.webm?t=1638279076\" type=\"video/webm; codecs=vp9\"><source src=\"https://shared.akamai.steamstatic.com/store_item_assets/steam/apps/1569720/extras/094890a683a8b7ce3970311df2ed80db.mp4?t=1638279076\" type=\"video/mp4\"></video></span><h2 class=\"bb_tag\" >GAME FEATURES</h2><ul class=\"bb_ul\"><li>Fantasy 3D character art and animation in a non-stop action shooting and dodge attack.<br></li><li>Single or team with 4 Player for the game challenge with 4 different title map.<br></li><li>Normal battle mode and survival battle mode for challenge</li></ul><h2 class=\"bb_tag\" >Steam Matchmaking and Lobbies</h2>Steam's peer to peer matchmaking API is built around to concept of a lobby can have up to 250 users in it and set of functions that enable users to find other users to play a game with. More information can visit <br><br><span class=\"bb_img_ctn\"><video class=\"bb_img\" autoplay muted loop playsinline poster=\"https://shared.akamai.steamstatic.com/store_item_assets/steam/apps/1569720/extras/045c9996a913671bc1e31e03cd77ac03.poster.avif?t=1638279076\" width=640 height=360 ><source src=\"https://shared.akamai.steamstatic.com/store_item_assets/steam/apps/1569720/extras/045c9996a913671bc1e31e03cd77ac03.webm?t=1638279076\" type=\"video/webm; codecs=vp9\"><source src=\"https://shared.akamai.steamstatic.com/store_item_assets/steam/apps/1569720/extras/045c9996a913671bc1e31e03cd77ac03.mp4?t=1638279076\" type=\"video/mp4\"></video></span>",
    "supported_languages": "英语",
    "header_image": "https://shared.akamai.steamstatic.com/store_item_assets/steam/apps/1569720/header.jpg?t=1638279076",
    "developers": [
      "CTRLZ Game Studio",
      "UNDO Academy"
    ],
    "publishers": [
      "UNDO Academy"
    ],
    "price_overview": {},
    "release_date": {
      "coming_soon": false,
      "date": "2021 年 11 月 30 日"
    },
    "categories": [
      {
        "id": 2,
        "description": "单人"
      },
      {
        "id": 1,
        "description": "多人"
      },
      {
        "id": 9,
        "description": "合作"
      },
      {
        "id": 38,
        "description": "在线合作"
      }
    ],
    "genres": [
      {
        "id": "1",
        "description": "动作"
      },
      {
        "id": "4",
        "description": "休闲"
      }
    ],
    "achievements": {
      "total": 49,
      "highlighted": [
        {
          "name": "Test Win Achievement",
          "path": "https://cdn.akamai.steamstatic.com/steamcommunity/public/images/apps/1569720/c0b78bb1574dd228a11c7efc3ce173335bd851ec.jpg"
        },
        {
          "name": "Ancient Lab: Bronze",
          "path": "https://cdn.akamai.steamstatic.com/steamcommunity/public/images/apps/1569720/b433f1a1a45c0102ea8981c947b1f4d4c92d52c2.jpg"
        },
        {
          "name": "Ancient Lab: Silver",
          "path": "https://cdn.akamai.steamstatic.com/steamcommunity/public/images/apps/1569720/e67318f5a60c6225e99a4155d8a16704250a51ee.jpg"
        },
        {
          "name": "Ancient Lab: Gold",
          "path": "https://cdn.akamai.steamstatic.com/steamcommunity/public/images/apps/1569720/b36ce237afa8cd62736c66fe4c876816411e322d.jpg"
        },
        {
          "name": "Ancient Lab: Diamond",
          "path": "https://cdn.akamai.steamstatic.com/steamcommunity/public/images/apps/1569720/1af6c46eb6453b1ac299a04b5822472bca98ad44.jpg"
        },
        {
          "name": "Ancient Lab Havoc: Bronze",
          "path": "https://cdn.akamai.steamstatic.com/steamcommunity/public/images/apps/1569720/2a3962a98b1b8a0e5ae64b5d7d523b898793fd0f.jpg"
        },
        {
          "name": "Ancient Lab Havoc: Silver",
          "path": "https://cdn.akamai.steamstatic.com/steamcommunity/public/images/apps/1569720/2bd0a0caf9a9989becf8b99053040094f21bc13b.jpg"
        },
        {
          "name": "Ancient Lab Havoc: Gold",
          "path": "https://cdn.akamai.steamstatic.com/steamcommunity/public/images/apps/1569720/7c44d2315f9c6eb1f9fce2bd3b80be7bbed2942b.jpg"
        },
        {
          "name": "Ancient Lab Havoc: Diamond",
          "path": "https://cdn.akamai.steamstatic.com/steamcommunity/public/images/apps/1569720/d0a9d19668a6951ce9b310ec049f4d551b3e63ef.jpg"
        },
        {
          "name": "Ancient Lab Survival: Bronze",
          "path": "https://cdn.akamai.steamstatic.com/steamcommunity/public/images/apps/1569720/3bc244a051279305c62b0e2fc8768e351c2d4301.jpg"
        }
      ]
    },
    "has_chinese": "false",
    "app_reviews": {
      "review_score_desc": "No user reviews",
      "total_positive": 0,
      "total_negative": 0,
      "total_reviews": 0
    }
  }
}