{
  "1602090": {
    "name": "Beware of Dog",
    "steam_appid": 1602090,
    "required_age": 0,
    "is_free": false,
    "description": "<p class=\"bb_paragraph\" ><strong>Beware Of Dog</strong> immerses players in an exciting third-person action-adventure/slasher game. Our heroes, Grandpa Jackhammer and his faithful Dog, found themselves face to face with the problem of meat shortages in stores. With fire and an 85-inch wrench, they carved their way to the goal, not even thinking about where they would end up in the end. The world had split and gone mad, but no one noticed. Life goes on, saleswomen are rude to customers, bears deliver pizza, elves engage in robbing late pedestrians. Everything is out of place here, and chaos reigns.</p><p class=\"bb_paragraph\" >You will take on the role of a retired steel mill worker, nicknamed Jackhammer for his inhuman strength, accompanied by his dog, named Dog. What started as a simple mission to buy meat at the grocery store will turn into an epic adventure in which our heroes will battle with criminal authorities, dragons, and other GIANT creatures, and discover that things, creatures, and substances are not always what they seem.</p><p class=\"bb_paragraph\" ></p><p class=\"bb_paragraph\" >Features: </p><p class=\"bb_paragraph\" ></p><p class=\"bb_paragraph\" >    • Fast-paced combat using a diverse arsenal of melee and ranged weapons. </p><p class=\"bb_paragraph\" >    • Combo system. </p><p class=\"bb_paragraph\" >    • Variety of unlockable skills and techniques. </p><p class=\"bb_paragraph\" >    • Uninterrupted gameplay without loading screens. </p><p class=\"bb_paragraph\" >    • Allies who assist in battle and lift your spirits with their witty remarks. </p><p class=\"bb_paragraph\" >    • A hero who can JUMP. </p><p class=\"bb_paragraph\" >    • Platforming sections and puzzles. </p><p class=\"bb_paragraph\" >    • Captivating storyline.</p>",
    "supported_languages": "英语<strong>*</strong>, 俄语<strong>*</strong><br><strong>*</strong>具有完全音频支持的语言",
    "header_image": "https://shared.akamai.steamstatic.com/store_item_assets/steam/apps/1602090/35c3b851f03e6cf8576cfde65d06268a8083748b/header.jpg?t=1770762469",
    "developers": [
      "DSW Games"
    ],
    "publishers": [
      "DSW Games"
    ],
    "price_overview": {},
    "release_date": {
      "coming_soon": true,
      "date": "2026 年"
    },
    "categories": [
      {
        "id": 2,
        "description": "单人"
      },
      {
        "id": 22,
        "description": "Steam 成就"
      },
      {
        "id": 28,
        "description": "完全支持控制器"
      },
      {
        "id": 23,
        "description": "Steam 云"
      },
      {
        "id": 62,
        "description": "家庭共享"
      }
    ],
    "genres": [
      {
        "id": "1",
        "description": "动作"
      },
      {
        "id": "25",
        "description": "冒险"
      },
      {
        "id": "23",
        "description": "独立"
      },
      {
        "id": "3",
        "description": "角色扮演"
      }
    ],
    "achievements": "none",
    "has_chinese": "false",
    "app_reviews": {
      "review_score_desc": "No user reviews",
      "total_positive": 0,
      "total_negative": 0,
      "total_reviews": 0
    }
  }
}