{
  "1628050": {
    "name": "Cats Organized Neatly - Paper Edition",
    "steam_appid": 1628050,
    "required_age": 0,
    "is_free": false,
    "description": "欢迎来到《整洁的猫》--纸质版<br><br>顾名思义，这是一个可打印的视频游戏《整齐划一的猫》的版本! 关卡和猫咪与基本游戏完全相同，这只是一种体验游戏的其他方式。<br><br>特别是在这个充满挑战的时代，这可以提供一个很好的方式来获得一些屏幕外的时间，专注于一些冥想的剪纸，或者把你的孩子们聚集在桌子周围，让猫咪很好地着色，然后再组织他们（整齐地）。<br><br><strong>你将得到一个包含以下内容的PDF文件。</strong><br><br><ul class=\"bb_ul\"><li>游戏规则<br></li><li>80个关卡，每个关卡都在自己的页面上<br></li><li>两套可以打印和剪裁的猫片。<br><ul class=\"bb_ul\"><li>像游戏中的版本一样预先着色<br></li><li>空白的，所以你可以用任何你喜欢的方式给猫咪重新着色!</li></ul></li></ul><br>我们希望你也会喜欢这种另类的游戏方式--发挥创意，享受乐趣吧 ♡♡<br><br>CatsOrganizedNeatly_Paper.pdf:<br><br><span class=\"bb_img_ctn\"><img class=\"bb_img\" src=\"https://shared.akamai.steamstatic.com/store_item_assets/steam/apps/1628050/extras/5cc6d6ea2f451e2b2da9d25d7533fb91.avif?t=1728890003\" width=276 height=214 /></span>",
    "supported_languages": "英语",
    "header_image": "https://shared.akamai.steamstatic.com/store_item_assets/steam/apps/1628050/header.jpg?t=1728890003",
    "developers": [
      "DU&I"
    ],
    "publishers": [
      "DU&I"
    ],
    "price_overview": {
      "currency": "CNY",
      "initial": 1100,
      "final": 550,
      "discount_percent": 50,
      "initial_formatted": "¥ 11.00",
      "final_formatted": "¥ 5.50"
    },
    "release_date": {
      "coming_soon": false,
      "date": "2021 年 7 月 7 日"
    },
    "categories": [
      {
        "id": 2,
        "description": "单人"
      },
      {
        "id": 21,
        "description": "DLC"
      },
      {
        "id": 62,
        "description": "家庭共享"
      }
    ],
    "genres": [
      {
        "id": "4",
        "description": "休闲"
      },
      {
        "id": "23",
        "description": "独立"
      }
    ],
    "achievements": "none",
    "has_chinese": "false",
    "app_reviews": {
      "review_score_desc": "No user reviews",
      "total_positive": 0,
      "total_negative": 0,
      "total_reviews": 0
    }
  }
}