{
  "2223540": {
    "name": "Hot 21",
    "steam_appid": 2223540,
    "required_age": 0,
    "is_free": false,
    "description": "<span class=\"bb_img_ctn\"><img class=\"bb_img\" src=\"https://shared.akamai.steamstatic.com/store_item_assets/steam/apps/2223540/extras/5bc3b1be3df203fb229624be650e0c32.avif?t=1676638596\" width=600 height=224 /></span><br><br>这是一款经典的美女Blackjack游戏，保证你可以轻松上手。<br><br><span class=\"bb_img_ctn\"><img class=\"bb_img\" src=\"https://shared.akamai.steamstatic.com/store_item_assets/steam/apps/2223540/extras/122364197496c9440e404ad4c1d694e9.avif?t=1676638596\" width=600 height=224 /></span><br><br>你可以根据自己的喜好选择不同的美女做为对手，只要你挑战成功，便可让女孩们为你跳一段火辣的舞蹈。<br><br><span class=\"bb_img_ctn\"><img class=\"bb_img\" src=\"https://shared.akamai.steamstatic.com/store_item_assets/steam/apps/2223540/extras/468cf066c601e08ad065d50871fd8a36.avif?t=1676638596\" width=600 height=224 /></span><br><span class=\"bb_img_ctn\"><img class=\"bb_img\" src=\"https://shared.akamai.steamstatic.com/store_item_assets/steam/apps/2223540/extras/3c9f65cb791dbcf6fea1ec38baa58a9d.avif?t=1676638596\" width=600 height=224 /></span><br><br>更重要的是，随着挑战的升级，你可以解锁更多火辣的表演。<br><br><span class=\"bb_img_ctn\"><img class=\"bb_img\" src=\"https://shared.akamai.steamstatic.com/store_item_assets/steam/apps/2223540/extras/c51fd15288ce937ff96db2316a8b352c.avif?t=1676638596\" width=600 height=684 /></span><br><span class=\"bb_img_ctn\"><img class=\"bb_img\" src=\"https://shared.akamai.steamstatic.com/store_item_assets/steam/apps/2223540/extras/b00b3fae705fb590d81e2ec7fede24d0.avif?t=1676638596\" width=600 height=684 /></span><br><span class=\"bb_img_ctn\"><img class=\"bb_img\" src=\"https://shared.akamai.steamstatic.com/store_item_assets/steam/apps/2223540/extras/e9a734f52a125df5798eba04da078f59.avif?t=1676638596\" width=600 height=684 /></span><br><span class=\"bb_img_ctn\"><img class=\"bb_img\" src=\"https://shared.akamai.steamstatic.com/store_item_assets/steam/apps/2223540/extras/c6adc3af7fb05be9e9b0106323316f61.avif?t=1676638596\" width=600 height=684 /></span><br><br><br>正在陆续制作中的是：<br>更多的角色<br>更多的服装<br>更多的舞曲<br>更多的场景<br><br>请保持关注，祝你好运！",
    "supported_languages": "英语<strong>*</strong><br><strong>*</strong>具有完全音频支持的语言",
    "header_image": "https://shared.akamai.steamstatic.com/store_item_assets/steam/apps/2223540/header.jpg?t=1676638596",
    "developers": [
      "B&W"
    ],
    "publishers": [
      "B&W"
    ],
    "price_overview": {
      "currency": "CNY",
      "initial": 1500,
      "final": 1500,
      "discount_percent": 0,
      "initial_formatted": "",
      "final_formatted": "¥ 15.00"
    },
    "release_date": {
      "coming_soon": false,
      "date": "2023 年 2 月 17 日"
    },
    "categories": [
      {
        "id": 2,
        "description": "单人"
      },
      {
        "id": 62,
        "description": "家庭共享"
      }
    ],
    "genres": [
      {
        "id": "1",
        "description": "动作"
      },
      {
        "id": "4",
        "description": "休闲"
      },
      {
        "id": "18",
        "description": "体育"
      }
    ],
    "achievements": "none",
    "has_chinese": "false",
    "app_reviews": {
      "review_score_desc": "1 user reviews",
      "total_positive": 1,
      "total_negative": 0,
      "total_reviews": 1
    },
    "type": "game"
  }
}