{
  "2254260": {
    "name": "Outmode - Official Soundtrack by Spaceinvader",
    "steam_appid": 2254260,
    "required_age": 0,
    "is_free": false,
    "description": "<span class=\"bb_img_ctn\"><img class=\"bb_img\" src=\"https://shared.akamai.steamstatic.com/store_item_assets/steam/apps/2254260/extras/0b55d16279198b4b459bdbadbf70bfc1.webp?t=1671729762\" width=557 height=23 /></span><br><br><strong>Experience the blast of synths like never before with this new official soundtrack composed by the renowned Synthwave artist, Spaceinvader!</strong><br><br>Contains 9 official tracks as heard in game, in both a lightweight .mp3 format and lossless .wav format. Contains the official album art in a .png format.<br><br>Also available on most major streaming services world wide.<br><br>Purchase this album with Outmode at a <strong>third of the price</strong> of retail!<br><br><span class=\"bb_img_ctn\"><img class=\"bb_img\" src=\"https://shared.akamai.steamstatic.com/store_item_assets/steam/apps/2254260/extras/0b55d16279198b4b459bdbadbf70bfc1.webp?t=1671729762\" width=557 height=23 /></span>",
    "supported_languages": "",
    "header_image": "https://shared.akamai.steamstatic.com/store_item_assets/steam/apps/2254260/header.jpg?t=1671729762",
    "developers": [
      "Rockateer",
      "Spaceinvader"
    ],
    "publishers": [],
    "price_overview": {
      "currency": "CNY",
      "initial": 600,
      "final": 600,
      "discount_percent": 0,
      "initial_formatted": "",
      "final_formatted": "¥ 6.00"
    },
    "release_date": {
      "coming_soon": false,
      "date": "2022 年 12 月 22 日"
    },
    "categories": [],
    "genres": [],
    "achievements": "none",
    "has_chinese": "false",
    "app_reviews": {
      "review_score_desc": "No user reviews",
      "total_positive": 0,
      "total_negative": 0,
      "total_reviews": 0
    },
    "type": "music"
  }
}