{
  "2324270": {
    "name": "Saint Patrick's Day Break",
    "steam_appid": 2324270,
    "required_age": 0,
    "is_free": false,
    "description": "Saint Patrick's Day Break is a retro arcade break out game with animated characters, powerups and custom music. Break Saint Patrick’s Day characters, objects, icons, and beers with a shamrock ball and paddle. Break your way thru the 30 levels. Saint Patrick's Day Break has simple controls and retro arcade action. Collect all the Saint Patrick’s Day powerups to stack powerups on your paddle and ball. (Laser, Fireball, Multi-ball, Sticky paddle, Mega Bomb, Wide paddle, Shield and Invincible paddle)<br />\r\n<br />\r\nTry to beat your high score and complete all the levels.",
    "supported_languages": "英语",
    "header_image": "https://shared.akamai.steamstatic.com/store_item_assets/steam/apps/2324270/header.jpg?t=1678815693",
    "developers": [
      "Smobile"
    ],
    "publishers": [
      "Smobile"
    ],
    "price_overview": {
      "currency": "CNY",
      "initial": 1500,
      "final": 1500,
      "discount_percent": 0,
      "initial_formatted": "",
      "final_formatted": "¥ 15.00"
    },
    "release_date": {
      "coming_soon": false,
      "date": "2023 年 3 月 14 日"
    },
    "categories": [
      {
        "id": 2,
        "description": "单人"
      },
      {
        "id": 22,
        "description": "Steam 成就"
      },
      {
        "id": 62,
        "description": "家庭共享"
      }
    ],
    "genres": [
      {
        "id": "4",
        "description": "休闲"
      },
      {
        "id": "23",
        "description": "独立"
      }
    ],
    "achievements": {
      "total": 37,
      "highlighted": [
        {
          "name": "Fast player",
          "path": "https://cdn.akamai.steamstatic.com/steamcommunity/public/images/apps/2324270/cdc89624142c43bc2432ec02190e2db50daf1bac.jpg"
        },
        {
          "name": "Slow player",
          "path": "https://cdn.akamai.steamstatic.com/steamcommunity/public/images/apps/2324270/ccd1433dd312ae0ef41764847fd81fd36b629d00.jpg"
        },
        {
          "name": "Angus defeated",
          "path": "https://cdn.akamai.steamstatic.com/steamcommunity/public/images/apps/2324270/683323fdfac1948a4f36539cdcff32e909eed1ba.jpg"
        },
        {
          "name": "Brennen defeated",
          "path": "https://cdn.akamai.steamstatic.com/steamcommunity/public/images/apps/2324270/282408236de946471ecc2a88fd5e34e23809904f.jpg"
        },
        {
          "name": "Connor defeated",
          "path": "https://cdn.akamai.steamstatic.com/steamcommunity/public/images/apps/2324270/41f7a7ca43d2e2abb3c5b1f9c36e0131c3623a50.jpg"
        },
        {
          "name": "Turbo player",
          "path": "https://cdn.akamai.steamstatic.com/steamcommunity/public/images/apps/2324270/3bf66ba75f68837a3ee68241da2bbedfe246a9b7.jpg"
        },
        {
          "name": "Sticky player",
          "path": "https://cdn.akamai.steamstatic.com/steamcommunity/public/images/apps/2324270/72dcff03850c47c2d34d71299a5e3133cc57c8cb.jpg"
        },
        {
          "name": "Shielded player",
          "path": "https://cdn.akamai.steamstatic.com/steamcommunity/public/images/apps/2324270/82acbf4b4943d0b7abb4830c0da156b9e5e62011.jpg"
        },
        {
          "name": "Invincible player",
          "path": "https://cdn.akamai.steamstatic.com/steamcommunity/public/images/apps/2324270/c425ec5c7f055d94c93c8ab736b6697b4943e607.jpg"
        },
        {
          "name": "Slow and steady",
          "path": "https://cdn.akamai.steamstatic.com/steamcommunity/public/images/apps/2324270/37ea0a1df7e82f95ae86177a47dd6701e198d0a8.jpg"
        }
      ]
    },
    "has_chinese": "false",
    "app_reviews": {
      "review_score_desc": "No user reviews",
      "total_positive": 0,
      "total_negative": 0,
      "total_reviews": 0
    },
    "type": "game"
  }
}