{
  "2377610": {
    "name": "Infasia",
    "steam_appid": 2377610,
    "required_age": 0,
    "is_free": false,
    "description": "<strong>Infasia</strong> est un RPG au tour par tour exigeant inspiré de l’univers du JDR éponyme créé en 2014.<br>Vous y incarnerez Xen, un voyageur poussé à l’exil qui rencontrera son destin lors de son arrivée à Core, la capitale Infasienne.<br>Entre guerres de clans et invasions de Sans-âmes, vous devrez vous forger un nom dans ce royaume pour accomplir vos objectifs.<br><br>Vous devrez prouver vos talents de stratège en pesant chacune de vos décisions. Dans Infasia, les affrontements sont à considérer comme des puzzle game dont la difficulté ne laisse pas de place au hasard ou au tâtonnement.<br><br>Dans ce jeu, vous retrouverez : <br><br>- 3 modes de difficulté (histoire, aventure et défis), pour s’adapter aux objectifs de jeu de chacun.<br>- 15 à 30 heures de jeu pour cette première partie.<br>- 4 classes originales, et peut-être plus si vous en avez l’étoffe.<br>- Un mode de combat au tour par tour innovant et exigeant<br>- Un scénario profond et mature corédigé par un maitre du jeu et ses joueurs depuis 2014<br><br>Auras-tu le courage d’entreprendre ce périple qui te mènera sur les traces de tes ancêtres infasiens ?<br><br>Pour la gloire des Fury !<br><br><span class=\"bb_img_ctn\"><img class=\"bb_img\" src=\"https://shared.akamai.steamstatic.com/store_item_assets/steam/apps/2377610/extras/e45187bb42a404d4f9d6902e932e29e3.avif?t=1743502366\" width=600 height=800 /></span>",
    "supported_languages": "法语<strong>*</strong><br><strong>*</strong>具有完全音频支持的语言",
    "header_image": "https://shared.akamai.steamstatic.com/store_item_assets/steam/apps/2377610/header.jpg?t=1743502366",
    "developers": [
      "Jarex"
    ],
    "publishers": [
      "Jarex"
    ],
    "price_overview": {
      "currency": "CNY",
      "initial": 1100,
      "final": 1100,
      "discount_percent": 0,
      "initial_formatted": "",
      "final_formatted": "¥ 11.00"
    },
    "release_date": {
      "coming_soon": false,
      "date": "2023 年 8 月 18 日"
    },
    "categories": [
      {
        "id": 2,
        "description": "单人"
      },
      {
        "id": 62,
        "description": "家庭共享"
      }
    ],
    "genres": [
      {
        "id": "25",
        "description": "冒险"
      },
      {
        "id": "3",
        "description": "角色扮演"
      }
    ],
    "achievements": "none",
    "has_chinese": "false",
    "app_reviews": {
      "review_score_desc": "No user reviews",
      "total_positive": 0,
      "total_negative": 0,
      "total_reviews": 0
    },
    "type": "game"
  }
}