{
  "2381620": {
    "name": "Steam Engine Simulator",
    "steam_appid": 2381620,
    "required_age": 0,
    "is_free": true,
    "description": "On January 21, 2023, AngeTheGreat released a video called &quot;Simulating a Steam Engine with C++&quot; which documented the creation of a simple steam engine simulation. This is that simulation now made into a simple game! Enjoy operating and listening to your own miniature virtual steam engine.",
    "supported_languages": "英语<strong>*</strong><br><strong>*</strong>具有完全音频支持的语言",
    "header_image": "https://shared.akamai.steamstatic.com/store_item_assets/steam/apps/2381620/header.jpg?t=1737208479",
    "developers": [
      "Ektorom Software Inc."
    ],
    "publishers": [
      "Ektorom Software Inc."
    ],
    "price_overview": {},
    "release_date": {
      "coming_soon": false,
      "date": "2023 年 6 月 7 日"
    },
    "categories": [
      {
        "id": 2,
        "description": "单人"
      },
      {
        "id": 22,
        "description": "Steam 成就"
      },
      {
        "id": 23,
        "description": "Steam 云"
      },
      {
        "id": 15,
        "description": "统计数据"
      }
    ],
    "genres": [
      {
        "id": "28",
        "description": "模拟"
      }
    ],
    "achievements": {
      "total": 18,
      "highlighted": [
        {
          "name": "Break It In",
          "path": "https://cdn.akamai.steamstatic.com/steamcommunity/public/images/apps/2381620/0dd8279f826e8f24aeff232afac56ba14e2f35ca.jpg"
        },
        {
          "name": "Casual Steamer",
          "path": "https://cdn.akamai.steamstatic.com/steamcommunity/public/images/apps/2381620/8015d61c0aa30056a99c96a7bdb73e5cf0ecc7fb.jpg"
        },
        {
          "name": "Tried and Tested",
          "path": "https://cdn.akamai.steamstatic.com/steamcommunity/public/images/apps/2381620/d1ecd6af21dcba0d37a9d49f2af5e812cae1e458.jpg"
        },
        {
          "name": "Hardcore Steamer",
          "path": "https://cdn.akamai.steamstatic.com/steamcommunity/public/images/apps/2381620/b0b22db4438e88c768f3d4029911fcf8f4ca7383.jpg"
        },
        {
          "name": "Time for a Rebuild",
          "path": "https://cdn.akamai.steamstatic.com/steamcommunity/public/images/apps/2381620/44135d0f21f0f8bb91c55f65be07b025593b28ca.jpg"
        },
        {
          "name": "Steam Enjoyer",
          "path": "https://cdn.akamai.steamstatic.com/steamcommunity/public/images/apps/2381620/0ccee5384141d8e61a9cd57cdf5558900986a925.jpg"
        },
        {
          "name": "Steam Lover",
          "path": "https://cdn.akamai.steamstatic.com/steamcommunity/public/images/apps/2381620/8dc2824d5f06b554192a18ef97e2b5dd265f35ec.jpg"
        },
        {
          "name": "Steam Fanatic",
          "path": "https://cdn.akamai.steamstatic.com/steamcommunity/public/images/apps/2381620/b53a5108e8b537dd4c3f3a92cec287ee2ae58a2f.jpg"
        },
        {
          "name": "Steam Freak",
          "path": "https://cdn.akamai.steamstatic.com/steamcommunity/public/images/apps/2381620/b60d13fc158d1dea93d4dab165e82d76241bc0c0.jpg"
        },
        {
          "name": "Steam Whistler",
          "path": "https://cdn.akamai.steamstatic.com/steamcommunity/public/images/apps/2381620/e8b0a0dbc86aa3fd0e1f7168079aaddba0c5c48a.jpg"
        }
      ]
    },
    "has_chinese": "false",
    "app_reviews": {
      "review_score_desc": "No user reviews",
      "total_positive": 0,
      "total_negative": 0,
      "total_reviews": 0
    },
    "type": "game"
  }
}