{
  "254440": {
    "name": "Pool Nation",
    "steam_appid": 254440,
    "required_age": 0,
    "is_free": false,
    "description": "Play POOL NATION and become mesmerised by our balls, entranced by our decals &amp; unashamedly attached to our cues, so join us please, &amp; just have fun playing pool!! WARNING: contains addictive content!! <br><br>Pool Nation, with <strong><u>WORKSHOP integration AVAILABLE NOW</u></strong> in our Crazy Mode <strong><u>the Box Of Tricks (Out Now)</u></strong>! But fear not, Pool Nation is not just about trick-shots, Pool Nation is a serious pool sim, the heart of the game is our world renowned Physics engine, the balls will behave as they would in the real world - Fancy a game with Aiming Assist turned off - you go ahead - Play Pool Nation Your way! <br><br>With <strong>eleven addictive game modes</strong>, including the adrenaline pumping <strong>Endurance</strong>, extensive career modes and seven exciting online modes including the <strong>new Speed Pool</strong>! Not forgetting <strong>the Box of Tricks</strong> coming soon to Steam, giving you the ability to imagine, build and share your most outlandish trickshots with the world. Utilizing a variety of objects, including <strong>Ramps, Pikes, Loop the Loops and Speed up strips</strong>, the Box of Tricks is limited only by your imagination. <br><br>With Pool Nation, <strong>gameplay is king</strong>! Online or offline, the ease of control gives you the ability to pull off shots you wouldn't dream of in the real world. The balls behave exactly as they should use the table surround to create the most unbelievable trickshots and view them back in super slow mo.<br><br>The graphics are as shiny and <strong>pixel-perfect </strong>as the physics, with beautiful locations, stunning exterior landscapes, eye-catching interiors, the ability to change the time of day, and customize your games with a huge array of balls, cues and table decals creating your ideal pool playing environment. Every detail has been considered and polished, from the super-detailed table baize and deforming cushions, to the explosions of chalk dust from the cue tip.<br><br>Pool Nation - the Community's Pool Game!",
    "supported_languages": "英语<strong>*</strong>, 法语, 意大利语, 德语, 西班牙语 - 西班牙<br><strong>*</strong>具有完全音频支持的语言",
    "header_image": "https://shared.akamai.steamstatic.com/store_item_assets/steam/apps/254440/header.jpg?t=1447358757",
    "developers": [
      "Cherry Pop Games"
    ],
    "publishers": [
      "Cherry Pop Games"
    ],
    "price_overview": {
      "currency": "CNY",
      "initial": 2900,
      "final": 2900,
      "discount_percent": 0,
      "initial_formatted": "",
      "final_formatted": "¥ 29.00"
    },
    "release_date": {
      "coming_soon": false,
      "date": "2013 年 10 月 18 日"
    },
    "categories": [
      {
        "id": 2,
        "description": "单人"
      },
      {
        "id": 1,
        "description": "多人"
      },
      {
        "id": 22,
        "description": "Steam 成就"
      },
      {
        "id": 28,
        "description": "完全支持控制器"
      },
      {
        "id": 29,
        "description": "Steam 集换式卡牌"
      },
      {
        "id": 30,
        "description": "Steam 创意工坊"
      },
      {
        "id": 23,
        "description": "Steam 云"
      },
      {
        "id": 25,
        "description": "Steam 排行榜"
      },
      {
        "id": 43,
        "description": "在电视上远程畅玩"
      },
      {
        "id": 62,
        "description": "家庭共享"
      }
    ],
    "genres": [
      {
        "id": "4",
        "description": "休闲"
      },
      {
        "id": "23",
        "description": "独立"
      },
      {
        "id": "28",
        "description": "模拟"
      },
      {
        "id": "18",
        "description": "体育"
      },
      {
        "id": "2",
        "description": "策略"
      }
    ],
    "achievements": {
      "total": 20,
      "highlighted": [
        {
          "name": "Win",
          "path": "https://cdn.akamai.steamstatic.com/steamcommunity/public/images/apps/254440/fecb3c44e7486ac06f0014144834a534a5dc8b99.jpg"
        },
        {
          "name": "Side Tracked",
          "path": "https://cdn.akamai.steamstatic.com/steamcommunity/public/images/apps/254440/c1673ee36646a57f49a55f09ddb205568eb4017c.jpg"
        },
        {
          "name": "Zen 8",
          "path": "https://cdn.akamai.steamstatic.com/steamcommunity/public/images/apps/254440/cc66dcd06b09584e815c69b5ca79f8724c7023e2.jpg"
        },
        {
          "name": "8 Ball Champion",
          "path": "https://cdn.akamai.steamstatic.com/steamcommunity/public/images/apps/254440/f14d2d57324ac626adcbf5f47f8514b8dba47986.jpg"
        },
        {
          "name": "All Star",
          "path": "https://cdn.akamai.steamstatic.com/steamcommunity/public/images/apps/254440/87abeee135fdc3f699c9571e9686a93353425b9c.jpg"
        },
        {
          "name": "Super Skill",
          "path": "https://cdn.akamai.steamstatic.com/steamcommunity/public/images/apps/254440/a361ded821514aadb5de4511b0dee42207e0f230.jpg"
        },
        {
          "name": "Jack Of All Trades",
          "path": "https://cdn.akamai.steamstatic.com/steamcommunity/public/images/apps/254440/738d15af5ad81268ef3111898abec4518a63d9b5.jpg"
        },
        {
          "name": "9 Ball Champion",
          "path": "https://cdn.akamai.steamstatic.com/steamcommunity/public/images/apps/254440/591bcd840dd793d679903598e695e6a27c9f6037.jpg"
        },
        {
          "name": "Super Streak",
          "path": "https://cdn.akamai.steamstatic.com/steamcommunity/public/images/apps/254440/81c327cdd4aa1a36ef5fe73e0dd09717162e6975.jpg"
        },
        {
          "name": "Champion",
          "path": "https://cdn.akamai.steamstatic.com/steamcommunity/public/images/apps/254440/5d09313a464d1ac8d7b07f44e0499497a00828d1.jpg"
        }
      ]
    },
    "has_chinese": "false",
    "app_reviews": {
      "review_score_desc": "Very Positive",
      "total_positive": 86,
      "total_negative": 13,
      "total_reviews": 99
    }
  }
}