{
  "3111860": {
    "name": "Crime Chronicles: The Hidden Truth",
    "steam_appid": 3111860,
    "required_age": 0,
    "is_free": false,
    "description": "Crime Chronicles: The Hidden Truth is an immersive adventure game in the genre of courtroom drama and detective investigation, inspired by the popular Ace Attorney series. Dive into a world of complex crimes and intense courtroom battles. In this game, you take on the role of Detective Liam Stark, working alongside Prosecutor Emilia Hall to solve a challenging murder case.<h2 class=\"bb_tag\" >Key Features:</h2><br><strong>Captivating Investigation: Delve into the details of the Edmund Harrison murder case, analyzing evidence, interrogating witnesses, and solving puzzles.<br><br>Dynamic Courtroom Drama: Participate in tense courtroom sessions where every testimony and choice you make impacts the case. Interact with the prosecutor and defense attorney to uncover the truth.<br><br>Choice-Driven Outcomes: Your decisions will shape the direction of the investigation and courtroom proceedings. Choose the right testimonies to strengthen the prosecution or challenge the defense.<br><br>Multiple Scenarios: Depending on your choices, the game offers different endings and story branches, making each playthrough unique.</strong><br><br>Crime Chronicles: The Hidden Truth provides a thrilling experience where every decision matters. Unravel the web of mysteries, find the truth, and achieve justice!",
    "supported_languages": "英语<strong>*</strong>, 俄语<br><strong>*</strong>具有完全音频支持的语言",
    "header_image": "https://shared.akamai.steamstatic.com/store_item_assets/steam/apps/3111860/header.jpg?t=1736014323",
    "developers": [
      "Skipertale"
    ],
    "publishers": [
      "Synergy Spire"
    ],
    "price_overview": {},
    "release_date": {
      "coming_soon": true,
      "date": "即将推出"
    },
    "categories": [
      {
        "id": 2,
        "description": "单人"
      },
      {
        "id": 22,
        "description": "Steam 成就"
      },
      {
        "id": 23,
        "description": "Steam 云"
      },
      {
        "id": 62,
        "description": "家庭共享"
      }
    ],
    "genres": [
      {
        "id": "4",
        "description": "休闲"
      },
      {
        "id": "23",
        "description": "独立"
      },
      {
        "id": "28",
        "description": "模拟"
      }
    ],
    "achievements": "none",
    "has_chinese": "false",
    "app_reviews": {
      "review_score_desc": "No user reviews",
      "total_positive": 0,
      "total_negative": 0,
      "total_reviews": 0
    },
    "type": "game"
  }
}