{
  "366290": {
    "name": "Carp Fishing Simulator",
    "steam_appid": 366290,
    "required_age": 0,
    "is_free": false,
    "description": "<strong>Carp Fishing Simulator aims to be the most advanced, authentic fishing experience on the market.</strong><br><br>Are you tired of not being able to cast where you want?<br>Tired of having a time limit?<br>Tired of being told by the announcer to lower the line tension?<br>Tired of information that you wouldn't know in real life given to you on the user interface?<br>Tired of catching fish after fish, no matter what you do?<br><br><strong>Then Carp Fishing Simulator is for you!</strong><br><br>Some of the features include:<h2 class=\"bb_tag\" >All tackle, equipment, venues &amp; species unlocked from the start, no grinding and no microtransactions!</h2><br><ul class=\"bb_ul\"><li> 22 Different species of fish to catch, including Pike, Perch &amp; Barbel<br></li><li> 15 Different Venues, some based on real life venues<br></li><li> 21 Different rigs, including rigs from Choice Rigs &amp; JPrecision Hooks<br></li><li> 42 Different Baits, including bait from real companies DNA Bait &amp; Active Bait<br></li><li> Real Time of day - Real accurate Time of day or night.<br></li><li> Real Dynamic weather - Changeable weather conditions taken from the real world location of the venues.<br></li><li> Seasons - Depending on the month you fish, you'll see seasonal changes which also affect the water/air temperature.<br></li><li> Full character customisation - Don't just choose a character, make your own!<br></li><li> Real AI - Fish are all completely controlled by complex AI, They are released in to the lake and do their own thing. No behaviour is pre-programmed.<br></li><li> Online multiplayer</li></ul>",
    "supported_languages": "英语<strong>*</strong>, 法语, 意大利语, 德语, 西班牙语 - 西班牙, 波兰语, 俄语<br><strong>*</strong>具有完全音频支持的语言",
    "header_image": "https://shared.akamai.steamstatic.com/store_item_assets/steam/apps/366290/header.jpg?t=1704737691",
    "developers": [
      "Dangerous Derk Interactive"
    ],
    "publishers": [
      "Dangerous Derk Interactive"
    ],
    "price_overview": {
      "currency": "CNY",
      "initial": 6700,
      "final": 6700,
      "discount_percent": 0,
      "initial_formatted": "",
      "final_formatted": "¥ 67.00"
    },
    "release_date": {
      "coming_soon": false,
      "date": "2021 年 10 月 14 日"
    },
    "categories": [
      {
        "id": 2,
        "description": "单人"
      },
      {
        "id": 1,
        "description": "多人"
      },
      {
        "id": 27,
        "description": "跨平台多人"
      },
      {
        "id": 28,
        "description": "完全支持控制器"
      },
      {
        "id": 23,
        "description": "Steam 云"
      },
      {
        "id": 25,
        "description": "Steam 排行榜"
      },
      {
        "id": 62,
        "description": "家庭共享"
      }
    ],
    "genres": [
      {
        "id": "28",
        "description": "模拟"
      },
      {
        "id": "18",
        "description": "体育"
      }
    ],
    "achievements": "none",
    "has_chinese": "false",
    "app_reviews": {
      "review_score_desc": "1 user reviews",
      "total_positive": 1,
      "total_negative": 0,
      "total_reviews": 1
    }
  }
}