{
  "541240": {
    "name": "Red's Kingdom",
    "steam_appid": 541240,
    "required_age": 0,
    "is_free": false,
    "description": "Mad King Mac has always caused trouble for his subjects, but stealing Red's winter stash of acorns, his prized golden nut AND kidnapping his father? That's going too far! Help lead Red on a journey across the land in search of his missing nuts, overcoming obstacles and unlocking abilities in this charmingly epic isometric puzzle adventure!<br />\r\n<br />\r\nSet out into the kingdom and you'll be on a roll… literally! Each area is a unique challenge to overcome – from throwing levers and battling Mac's goons to hitting ramps, sticking on tar and much more, the puzzles keep on coming. Unlock special abilities and return to previously explored areas to access new routes, or hunt for secrets that can help in your quest to teach Mad King Mac a lesson he'll never forget!<br />\r\n<br />\r\n• Part puzzle, part adventure – roam the kingdom solving puzzles to find new routes and places to explore.<br />\r\n<br />\r\n• Battle Mad King Mac's goons, meet new friends and discover new abilities to advance your quest.<br />\r\n<br />\r\n• Keep a keen eye out for hidden paths and uncover secrets that can help you on your journey!<br />\r\n<br />\r\n• Save your father, reclaim the prized golden nut and defeat Mad King Mac once and for all!",
    "supported_languages": "英语<strong>*</strong>, 法语<strong>*</strong>, 意大利语<strong>*</strong>, 德语<strong>*</strong>, 西班牙语 - 西班牙<strong>*</strong>, 葡萄牙语 - 葡萄牙<strong>*</strong>, 葡萄牙语 - 巴西<strong>*</strong>, 俄语<strong>*</strong><br><strong>*</strong>具有完全音频支持的语言",
    "header_image": "https://shared.akamai.steamstatic.com/store_item_assets/steam/apps/541240/header.jpg?t=1682413713",
    "developers": [
      "Cobra Mobile"
    ],
    "publishers": [
      "Cobra Mobile"
    ],
    "price_overview": {
      "currency": "CNY",
      "initial": 3600,
      "final": 3600,
      "discount_percent": 0,
      "initial_formatted": "",
      "final_formatted": "¥ 36.00"
    },
    "release_date": {
      "coming_soon": false,
      "date": "2017 年 1 月 19 日"
    },
    "categories": [
      {
        "id": 2,
        "description": "单人"
      },
      {
        "id": 22,
        "description": "Steam 成就"
      },
      {
        "id": 28,
        "description": "完全支持控制器"
      },
      {
        "id": 29,
        "description": "Steam 集换式卡牌"
      },
      {
        "id": 23,
        "description": "Steam 云"
      },
      {
        "id": 25,
        "description": "Steam 排行榜"
      },
      {
        "id": 62,
        "description": "家庭共享"
      }
    ],
    "genres": [
      {
        "id": "1",
        "description": "动作"
      },
      {
        "id": "25",
        "description": "冒险"
      },
      {
        "id": "4",
        "description": "休闲"
      },
      {
        "id": "23",
        "description": "独立"
      }
    ],
    "achievements": {
      "total": 21,
      "highlighted": [
        {
          "name": "Complete Game",
          "path": "https://cdn.akamai.steamstatic.com/steamcommunity/public/images/apps/541240/88e458bac7e356c258526849c5500c0d800da0c3.jpg"
        },
        {
          "name": "Complete Game without dying",
          "path": "https://cdn.akamai.steamstatic.com/steamcommunity/public/images/apps/541240/4110520afdd309518f659f9416d29b2fa334999c.jpg"
        },
        {
          "name": "Complete game under 90 minutes",
          "path": "https://cdn.akamai.steamstatic.com/steamcommunity/public/images/apps/541240/62890be1f9c4a55a0e420c021cc7411de92d31b0.jpg"
        },
        {
          "name": "Get the medallion",
          "path": "https://cdn.akamai.steamstatic.com/steamcommunity/public/images/apps/541240/6d1837f5cee2aa1d1f67470daab09a37c3416852.jpg"
        },
        {
          "name": "Get the Wing Suit",
          "path": "https://cdn.akamai.steamstatic.com/steamcommunity/public/images/apps/541240/773489e93ac3f9dd6e0bb3e37a5cbe4f2ab5ffdc.jpg"
        },
        {
          "name": "Get the Glowing Mushroom",
          "path": "https://cdn.akamai.steamstatic.com/steamcommunity/public/images/apps/541240/9a3a1547b0f98367dff0ce947417f2da4b40b47b.jpg"
        },
        {
          "name": "Collect 100 Nuts",
          "path": "https://cdn.akamai.steamstatic.com/steamcommunity/public/images/apps/541240/ad4863c1bcbb706d3986917febd99ae296e466be.jpg"
        },
        {
          "name": "Collect 500 Nuts",
          "path": "https://cdn.akamai.steamstatic.com/steamcommunity/public/images/apps/541240/cf3f29f543433b5aceb80448920bf95e8efe4492.jpg"
        },
        {
          "name": "Collect 1000 Nuts",
          "path": "https://cdn.akamai.steamstatic.com/steamcommunity/public/images/apps/541240/f69a375036628dfcdaa2475ed55e0722e90df8e2.jpg"
        },
        {
          "name": "Have 5 Hearts",
          "path": "https://cdn.akamai.steamstatic.com/steamcommunity/public/images/apps/541240/0377b1f3245899628b8f53fa84305e571b4b8399.jpg"
        }
      ]
    },
    "has_chinese": "false",
    "app_reviews": {
      "review_score_desc": "1 user reviews",
      "total_positive": 1,
      "total_negative": 0,
      "total_reviews": 1
    }
  }
}